aiida_nanotech_empa/__init__.py
aiida_nanotech_empa/helpers.py
aiida_nanotech_empa/version.py
aiida_nanotech_empa/parsers/__init__.py
aiida_nanotech_empa/parsers/cp2k_gw_parser.py
aiida_nanotech_empa/parsers/cp2k_neb_parser.py
aiida_nanotech_empa/parsers/cubegen_pymol_parser.py
aiida_nanotech_empa/parsers/gaussian_casscf_parser.py
aiida_nanotech_empa/parsers/pp_parser.py
aiida_nanotech_empa/plugins/__init__.py
aiida_nanotech_empa/plugins/afm.py
aiida_nanotech_empa/plugins/hrstm.py
aiida_nanotech_empa/plugins/overlap.py
aiida_nanotech_empa/plugins/stm.py
aiida_nanotech_empa/schedulers/__init__.py
aiida_nanotech_empa/schedulers/lsf_ethz_euler.py
aiida_nanotech_empa/schedulers/slurm_ethz_euler.py
aiida_nanotech_empa/utils/__init__.py
aiida_nanotech_empa/utils/analyze_structure.py
aiida_nanotech_empa/utils/common_utils.py
aiida_nanotech_empa/utils/cube_utils.py
aiida_nanotech_empa/utils/cycle_tools.py
aiida_nanotech_empa/utils/gaussian_wcs_postprocess.py
aiida_nanotech_empa/utils/igor.py
aiida_nanotech_empa/utils/nmr.py
aiida_nanotech_empa/utils/pymol_render.py
aiida_nanotech_empa/utils/split_structure.py
aiida_nanotech_empa/utils/stm_tools.py
aiida_nanotech_empa/workflows/__init__.py
aiida_nanotech_empa/workflows/cp2k/__init__.py
aiida_nanotech_empa/workflows/cp2k/adsorbed_gw_ic_workchain.py
aiida_nanotech_empa/workflows/cp2k/afm_workchain.py
aiida_nanotech_empa/workflows/cp2k/cp2k_utils.py
aiida_nanotech_empa/workflows/cp2k/diag_workchain.py
aiida_nanotech_empa/workflows/cp2k/fragment_separation.py
aiida_nanotech_empa/workflows/cp2k/geo_opt_workchain.py
aiida_nanotech_empa/workflows/cp2k/hrstm_workchain.py
aiida_nanotech_empa/workflows/cp2k/molecule_gw_workchain.py
aiida_nanotech_empa/workflows/cp2k/molecule_opt_gw_workchain.py
aiida_nanotech_empa/workflows/cp2k/neb_workchain.py
aiida_nanotech_empa/workflows/cp2k/orbitals_workchain.py
aiida_nanotech_empa/workflows/cp2k/pdos_workchain.py
aiida_nanotech_empa/workflows/cp2k/phonons_workchain.py
aiida_nanotech_empa-1.0.0b12.dist-info/entry_points.txt
aiida_nanotech_empa-1.0.0b12.dist-info/licenses/LICENSE
aiida_nanotech_empa-1.0.0b12.dist-info/WHEEL
aiida_nanotech_empa-1.0.0b12.dist-info/METADATA
aiida_nanotech_empa-1.0.0b12.dist-info/RECORD
