Metadata-Version: 2.4
Name: aiida-nanotech-empa
Version: 1.0.0b12
Summary: AiiDA plugins and workflows developed at nanotech@surfaces group from Empa.
Author: nanotech@surfaces
Requires-Python: >=3.9
Classifier: Development Status :: 5 - Production/Stable
Classifier: Framework :: AiiDA
Classifier: Intended Audience :: Science/Research
Classifier: License :: OSI Approved :: MIT License
Classifier: Natural Language :: English
Classifier: Programming Language :: Python
Classifier: Programming Language :: Python :: 3.9
Classifier: Programming Language :: Python :: 3.10
Classifier: Programming Language :: Python :: 3.11
Classifier: Topic :: Scientific/Engineering
License-File: LICENSE
Requires-Dist: aiida-core>=2.6,<3.0.0
Requires-Dist: aiida-quantumespresso~=4.8
Requires-Dist: aiida-pseudo~=1.7
Requires-Dist: aiida-cp2k>=2.1.1,<3.0.0
Requires-Dist: ase~=3.21
Requires-Dist: aiida-gaussian~=2.0
Requires-Dist: aiida-shell
Requires-Dist: pillow>=8.0.0
Requires-Dist: more-itertools
Requires-Dist: pgtest~=1.3.1 ; extra == "dev"
Requires-Dist: pytest~=6.0 ; extra == "dev"
Requires-Dist: pytest-cov ; extra == "dev"
Requires-Dist: pre-commit>=2.19 ; extra == "dev"
Requires-Dist: bumpver==2022.1119 ; extra == "dev"
Requires-Dist: coverage ; extra == "dev"
Project-URL: Homepage, https://github.com/nanotech-empa/aiida-nanotech-empa
Provides-Extra: dev
